waccy_quickbooks/__init__.py
waccy_quickbooks/extractor.py
waccy_quickbooks-0.1.0.dist-info/METADATA
waccy_quickbooks-0.1.0.dist-info/WHEEL
waccy_quickbooks-0.1.0.dist-info/entry_points.txt
waccy_quickbooks-0.1.0.dist-info/RECORD
